CONTRIBUTING.md
LICENSE
MANIFEST.in
Makefile
README.md
package-lock.json
package.json
pyproject.toml
setup.py
.idea/.gitignore
.idea/misc.xml
.idea/modules.xml
.idea/osd-slides.iml
.idea/vcs.xml
.idea/inspectionProfiles/Project_Default.xml
.idea/inspectionProfiles/profiles_settings.xml
docs/Makefile
docs/conf.py
docs/index.md
docs/make.bat
docs/modules.rst
docs/osd_slides.rst
docs/requirements.txt
examples/searching_example.gif
osd_slides/__init__.py
osd_slides/__main__.py
osd_slides/main.py
osd_slides/search.py
osd_slides.egg-info/PKG-INFO
osd_slides.egg-info/SOURCES.txt
osd_slides.egg-info/dependency_links.txt
osd_slides.egg-info/requires.txt
osd_slides.egg-info/top_level.txt
osd_slides/.pytest_cache/.gitignore
osd_slides/.pytest_cache/CACHEDIR.TAG
osd_slides/.pytest_cache/README.md
osd_slides/.pytest_cache/v/cache/lastfailed
osd_slides/.pytest_cache/v/cache/nodeids
osd_slides/.pytest_cache/v/cache/stepwise
osd_slides/tests/__init__.py
osd_slides/tests/test_all.py