Metadata-Version: 2.1
Name: osd-slides
Version: 0.2.1
Summary: osd-slides is a tool to download Prof. Paine's slides through terminal with one command.
Author-email: Kutay Karakas <kutay@karakas.co>
License: MIT License
Project-URL: repository, https://github.com/kkarakas/osd-slides
Classifier: Development Status :: 2 - Pre-Alpha
Classifier: Programming Language :: Python :: Implementation :: CPython
Classifier: Programming Language :: Python :: Implementation :: PyPy
Classifier: Programming Language :: Python :: 3
Classifier: Programming Language :: Python :: 3.7
Classifier: Programming Language :: Python :: 3.8
Classifier: Programming Language :: Python :: 3.9
Classifier: Programming Language :: Python :: 3.10
Classifier: Programming Language :: Python :: 3.11
Requires-Python: >=3.7
Provides-Extra: develop
License-File: LICENSE
